{
    "data": [
        {
            "title":"COOK",
            "id":"1",
            "listStyle":[
                {
                    "id":"1",
                    "title":"Ẩm thực Việt Nam",
                    "listTitle":[{
                    "title":"Món ngon hằng ngày",
                        "id":"1",
                        "menu":[{
                                "id":1,
                                "name":"Gà nướng ngũ vị",
                                "describe":"Đây là món ăn truyền thống dinh dưỡng cao vitaminc nhiều...",
                                "ingredient":["1,5kg gà ta", "50g ớt sừng không cay", "20g ớt xa" ,"10g ớt khô Huế", "20g hành tím khô"," 20 tỏi"," 20g tương ớt"," 10ml màu điều 10g bột thịt gà"," súp nền lẩu Thái 10ml dầu ăn"],
                                "making":["Bước 1:ấy hành tím bóc sạch vỏ rửa sạch và tỏi cũng làm tương tự như thế để qua một bên trong khay nhỏ để sau đó chế cho tiện lợi.",
                                    "Bước 2: tổng hợp gia vị đã chuẩn bị sẵn ở trên vào máy sinh tố và cứ thế xay thật nhuyễn. Sau đó cho nước xốt ra một to lớn hoặc có thể để nguyên trong máy xay rồi tắt máy",
                                    "Bước 3:lấy gà đã được làm sạch rồi đem ướp với nước xốt đã vừa mới chế biến khi nãy vào bên trong cũng như bên ngoài da của gà. Và chúng ta nên để khoảng 20 phút cho nước xốt thấm đều. Sau đó tiếp tục cho vào lò nướng ở nhiệt độ 180 nướng khoảng 25 phút. Sau khi gà chín vàng thị lấy ra"],
                                "price":50000,
                                "numberPeople":4,
                                "Prepare":"30 minute",
                                "Cook":"6 hour"
                                },
        
                                {"id":"2",
                                "name":"Thịt lợn xào tỏi",
                                "describe":"Món ăn giàu sắt tốt cho da",
                                "ingredient":["500g gà ta"," Mè đen: 5g"," Mật ong: 1 muỗng"," Nước tương: 1 thìa"," Nước mắm: 1 thìa"," Gừng: ½ củ"," Hành lá: 10g"],
                                "making":["Bước 1:cho một ít nước tương, nước mắm, Knorr Gia Vị Hoàn Chỉnh - Thịt Kho và mật ong vào một bát nhỏ rồi khuấy đều",
                                    "Bước 2: Các bạn cho đùi gà vào bát nước ướp vừa pha lúc nãy rồi dùng muỗng thoa đều nước tương lên những miếng gà và cho vào tủ lạnh ướp khoảng 15 phút. Bạn có thể dùng tăm hoặc dĩa xiên vài lỗ trên đùi gà để phần gia vị có thể thấm nhanh và kỹ vào thịt gà hơn",
                                    "Bước 3:xếp hành và gừng trải đều lên khay nướng, rồi để những miếng gà lên phía trên cùng. Sau đó, bạn cho khay vào lò, nướng ở nhiệt độ khoảng 200 độ c, nướng trong vòng 30 phút. Bạn nhớ canh trở gà liên tục để gà có thể chín đều. Khi đùi gà có màu vàng cánh gián đẹp mắt thì hãy cho ra ngoài.",
                                    "Bước 4:Cuối cùng, sau khi hoàn tất việc nướng thịt gà rồi thì hãy xếp thịt gà ra đĩa và rắc mè lên phía trên đĩa và trang trí với rau sống, dưa leo, cà chua tùy sở thích của bạn. Phần nước sốt còn lại bạn có thể dùng để trộn ăn với cơm rất ngon."],
                                "price":40000,
                                "numberPeople":3,
                                "Prepare":"30 minute",
                                "Cook":"6 hour"
                            }
                        ]
       
                    },
                    {
                        "title":"COMBO gia đình",
                        "id":"2",
                        "menu":[
                            {
                                "id":1,
                                "name":"COMBO 1:Mực nhồi thịt sốt cà chua - Rau lang luộc chấm mắm - Cà pháo - Canh mướp nấu rau dền",
                                "describe":"Đây là món ăn truyền thống dinh dưỡng cao vitaminc nhiều...",
                                "ingredient":[{
                                    "name":"Mực nhồi thịt sốt cà chua",
                                    "ingredient":["1,5kg gà ta", "50g ớt sừng không cay", "20g ớt xa" ,"10g ớt khô Huế", "20g hành tím khô"," 20 tỏi"," 20g tương ớt"," 10ml màu điều 10g bột thịt gà"," súp nền lẩu Thái 10ml dầu ăn"],
                                    "making":["Bước 1:ấy hành tím bóc sạch vỏ rửa sạch và tỏi cũng làm tương tự như thế để qua một bên trong khay nhỏ để sau đó chế cho tiện lợi.",
                                        "Bước 2: tổng hợp gia vị đã chuẩn bị sẵn ở trên vào máy sinh tố và cứ thế xay thật nhuyễn. Sau đó cho nước xốt ra một to lớn hoặc có thể để nguyên trong máy xay rồi tắt máy",
                                        "Bước 3:lấy gà đã được làm sạch rồi đem ướp với nước xốt đã vừa mới chế biến khi nãy vào bên trong cũng như bên ngoài da của gà. Và chúng ta nên để khoảng 20 phút cho nước xốt thấm đều. Sau đó tiếp tục cho vào lò nướng ở nhiệt độ 180 nướng khoảng 25 phút. Sau khi gà chín vàng thị lấy ra"]
                                    },
                                    {
                                    "name":"Rau lang luộc chấm mắm",
                                    "ingredient":["1,5kg gà ta", "50g ớt sừng không cay", "20g ớt xa" ,"10g ớt khô Huế", "20g hành tím khô"," 20 tỏi"," 20g tương ớt"," 10ml màu điều 10g bột thịt gà"," súp nền lẩu Thái 10ml dầu ăn"],
                                    "making":["Bước 1:ấy hành tím bóc sạch vỏ rửa sạch và tỏi cũng làm tương tự như thế để qua một bên trong khay nhỏ để sau đó chế cho tiện lợi.",
                                        "Bước 2: tổng hợp gia vị đã chuẩn bị sẵn ở trên vào máy sinh tố và cứ thế xay thật nhuyễn. Sau đó cho nước xốt ra một to lớn hoặc có thể để nguyên trong máy xay rồi tắt máy",
                                        "Bước 3:lấy gà đã được làm sạch rồi đem ướp với nước xốt đã vừa mới chế biến khi nãy vào bên trong cũng như bên ngoài da của gà. Và chúng ta nên để khoảng 20 phút cho nước xốt thấm đều. Sau đó tiếp tục cho vào lò nướng ở nhiệt độ 180 nướng khoảng 25 phút. Sau khi gà chín vàng thị lấy ra"]
                                    },
                                    {
                                    "name":"Canh mướp nấu rau dền",
                                    "ingredient":["1,5kg gà ta", "50g ớt sừng không cay", "20g ớt xa" ,"10g ớt khô Huế", "20g hành tím khô"," 20 tỏi"," 20g tương ớt"," 10ml màu điều 10g bột thịt gà"," súp nền lẩu Thái 10ml dầu ăn"],
                                    "making":["Bước 1:ấy hành tím bóc sạch vỏ rửa sạch và tỏi cũng làm tương tự như thế để qua một bên trong khay nhỏ để sau đó chế cho tiện lợi.",
                                        "Bước 2: tổng hợp gia vị đã chuẩn bị sẵn ở trên vào máy sinh tố và cứ thế xay thật nhuyễn. Sau đó cho nước xốt ra một to lớn hoặc có thể để nguyên trong máy xay rồi tắt máy",
                                        "Bước 3:lấy gà đã được làm sạch rồi đem ướp với nước xốt đã vừa mới chế biến khi nãy vào bên trong cũng như bên ngoài da của gà. Và chúng ta nên để khoảng 20 phút cho nước xốt thấm đều. Sau đó tiếp tục cho vào lò nướng ở nhiệt độ 180 nướng khoảng 25 phút. Sau khi gà chín vàng thị lấy ra"]
                                    }
                                ],
                                "price":50000,
                                "numberPeople":4
                            }
                        ]
                    }
                ]
                    
                },
                {
                    "id":"2",
                    "titleChild":"Ẩm thực nước ngoài",
                    "listDish":[
                        {
                            "id":"1",
                            "name":"Stove Pot Roast With Mashed Potatoes",
                            "describe":"682 calo; chất đạm 31,2g; cacbohydrat 62,6g; chất béo 34,6g; cholesterol 120,3mg; natri 756,7mg",
                            "ingredient":[" (3 pound) thịt bò nướng"," muối và tiêu đen xay để nếm",
                                
                                "4 lon nước dùng bò cô đặc (chẳng hạn như Campbell's®)",
                                
                                "1 ly nước",
                                
                               " 1 củ hành trắng cắt miếng lớn",
                                
                                "5 tép tỏi",
                                
                                "1 gói (16 ounce) cà rốt, gọt vỏ",
                                
                                "1 nhánh hương thảo tươi",
                                
                                "Khoai tây nghiền:5 pound khoai tây Yukon Gold, gọt vỏ và cắt hạt 1 (12 ounce) có thể là sữa bay hơi, hoặc khi cần thiết",
                                "½ cốc bơ",
                                
                                "muối để nếm"],
                            "making":["Bước 1:Nêm món thịt nướng với muối và tiêu đen; nướng trong chảo lớn, sâu lòng hoặc lò nướng kiểu Hà Lan ở lửa vừa cho đến khi chín vàng, khoảng 10 phút mỗi mặt.",
                                "Bước 2: Đổ nước luộc thịt bò và nước vào chảo rang. Xếp hành và tỏi băm xung quanh miếng thịt. Trải cà rốt rang trên đỉnh và đặt nhánh hương thảo trên đỉnh cà rốt. Vặn lửa ở mức vừa phải và đun nhỏ lửa cho đến khi chín mềm, khoảng 6 giờ",
                                "Bước 3:Cho khoai tây vào nồi lớn đun sôi; giảm lửa nhỏ và đun cho đến khi mềm, khoảng 30 phút. Xả nước. Nghiền khoai tây với bơ và một nửa lượng sữa đã bốc hơi cho đến khi mịn; từ từ nghiền sữa bay hơi còn lại vào khoai tây để đạt được độ đặc mong muốn. Mùa muối."
                                ,"Bước 4:Lấy 1 hoặc 2 tép tỏi ra khỏi chảo và băm nhuyễn các tép tỏi trên lớp rang; phục vụ với khoai tây nghiền."],
                            "price":100000,
                            "numberPeople":4,
                            "Prepare":"30 minute",
                            "Cook":"6 hour"
                        }
                    ]
                }              
            ]

        },
        
        {
            "title":"Market",
            "id":2,
            "food":[
                {
                    "titleChild":"Meat",
                    "id":"1",
                    "listFood":[
                        {
                            "id":"1",
                            "name":"Thịt heo Mỹ",
                            "quantitative":"500g",
                            "price":100000
                        },
                        {
                            "id":"2",
                            "name":"Thịt bò Mỹ",
                            "quantitative":"500g",
                            "price":45000
                        }
                    ]
                },
                {
                    "titleChild":"Dring",
                    "id":"2",
                    "listFood":[
                        {
                            "id":"1",
                            "name":"Coca",
                            "quantitative":1,
                            "price":10000
                        },
                        {
                            "id":"2",
                            "name":"7-Up",
                            "quantitative":1,
                            "price":15000
                        }
                    ]
                }
            ]

        }
    ]
}